functions_by_aizhan_user/math_functions.py
functions_by_aizhan_user-0.3.0.dist-info/WHEEL
functions_by_aizhan_user-0.3.0.dist-info/METADATA
functions_by_aizhan_user-0.3.0.dist-info/RECORD
