Metadata-Version: 2.1
Name: functions-by-aizhan-user
Version: 0.3.0
Summary: This is our test project
Author: Aizhan Myrzakimova
Author-email: amyrzakimova@gmail.com
Requires-Python: >=3.10,<4.0
Classifier: Programming Language :: Python :: 3
Classifier: Programming Language :: Python :: 3.10
Classifier: Programming Language :: Python :: 3.11
